lbforaging/__init__.py
lbforaging/agents/__init__.py
lbforaging/agents/agent.py
lbforaging/agents/hba.py
lbforaging/agents/heuristic_agent.py
lbforaging/agents/monte_carlo.py
lbforaging/agents/nn_agent.py
lbforaging/agents/q_agent.py
lbforaging/agents/random_agent.py
lbforaging/foraging/__init__.py
lbforaging/foraging/environment.py
lbforaging/foraging/rendering.py
lbforaging/foraging/icons/agent.png
lbforaging/foraging/icons/apple.png
lbforaging-2.0.0.dist-info/LICENSE
lbforaging-2.0.0.dist-info/METADATA
lbforaging-2.0.0.dist-info/WHEEL
lbforaging-2.0.0.dist-info/top_level.txt
lbforaging-2.0.0.dist-info/RECORD
