Metadata-Version: 2.1
Name: lbforaging
Version: 2.0.0
Summary: Level Based Foraging Environment
Home-page: https://github.com/semitable/lb-foraging
Author: Filippos Christianos
Classifier: Intended Audience :: Developers
Classifier: Programming Language :: Python :: 3.4
Classifier: Programming Language :: Python :: 3.5
Classifier: Programming Language :: Python :: 3.6
Classifier: Programming Language :: Python :: 3.7
License-File: LICENSE
Requires-Dist: numpy
Requires-Dist: gymnasium
Requires-Dist: pyglet <2
Requires-Dist: six
Provides-Extra: test
Requires-Dist: pytest ; extra == 'test'
